data_lab/__init__.py
data_lab/data_lab.py
data_lab/get_data.py
data_lab/get_fillna.py
data_lab/labcut_deploy.py
data_lab/labcut_json.py
data_lab/labcut_reliability_deploy.py
data_lab/labcut_reliability_train.py
data_lab/labcut_train.py
data_lab/mlops-key 제거 파일 ( 업로드 됨 0.0.0.3 ) (1).py
data_lab/mlops.py
data_lab/mlops_deploy.py
data_lab/mlops_json.py
data_lab/mlops_train.py
data_lab/silo_deploy.py
dongwha_datalab-0.0.0.38.dist-info/METADATA
dongwha_datalab-0.0.0.38.dist-info/WHEEL
dongwha_datalab-0.0.0.38.dist-info/top_level.txt
dongwha_datalab-0.0.0.38.dist-info/RECORD
