Metadata-Version: 2.1
Name: dongwha-datalab
Version: 0.0.0.38
Summary: 동화기업 데이터랩에서 만든 통합 패키지이다.
Home-page: 
Author: 
Author-email: 
License: MIT
Requires-Python: >=3.4
Requires-Dist: boto3
Requires-Dist: pymongo
Requires-Dist: panel
Requires-Dist: ipyfilechooser
